{
  "faqs": [
    {
      "id": 1,
      "category": "General",
      "question": "Cilat zona mbuloni?",
      "answer": "Ne me krenari u sh\u00ebrbejm\u00eb Prishtin\u00eb, Kosov\u00eb, Prizren, Kosov\u00eb, Ferizaj, Kosov\u00eb, Gjilan, Kosov\u00eb, s\u00eb bashku me zonat p\u00ebrreth. Sh\u00ebrbimet tona profesionale jan\u00eb t\u00eb disponueshme n\u00eb t\u00eb gjitha k\u00ebto komunitete."
    },
    {
      "id": 2,
      "category": "General",
      "question": "Si mund t'ju kontaktoj?",
      "answer": "Ju mund t\u00eb na kontaktoni n\u00eb 044 239 757 ose t\u00eb na d\u00ebrgoni email n\u00eb info@bujoelectric.com. Ne jemi n\u00eb dispozicion 24/7."
    },
    {
      "id": 3,
      "category": "Services",
      "question": "\u00c7far\u00eb sh\u00ebrbimesh ofroni?",
      "answer": "Ne ofrojm\u00eb Instalime Elektrike, Riparime Elektrike, Mir\u00ebmbajtje Elektrike, Ndri\u00e7im & Energji, Sisteme Speciale. Na kontaktoni p\u00ebr nj\u00eb konsultim falas p\u00ebr t\u00eb diskutuar nevojat tuaja specifike."
    },
    {
      "id": 4,
      "category": "Services",
      "question": "A ofroni vler\u00ebsime falas?",
      "answer": "Po, ne ofrojm\u00eb vler\u00ebsime plot\u00ebsisht falas dhe pa detyrime p\u00ebr t\u00eb gjitha sh\u00ebrbimet tona. Na kontaktoni n\u00eb 044 239 757 p\u00ebr t\u00eb caktuar vler\u00ebsimin tuaj."
    },
    {
      "id": 5,
      "category": "Pricing",
      "question": "Sa kushtojn\u00eb sh\u00ebrbimet tuaja?",
      "answer": "\u00c7mimi ndryshon n\u00eb var\u00ebsi t\u00eb fush\u00ebveprimit t\u00eb pun\u00ebs, materialeve t\u00eb nevojshme dhe k\u00ebrkesave specifike. Ne ofrojm\u00eb \u00e7mime transparente, paraprake pa tarifa t\u00eb fshehura. Na kontaktoni p\u00ebr nj\u00eb vler\u00ebsim falas."
    },
    {
      "id": 6,
      "category": "Scheduling",
      "question": "Sa shpejt mund t\u00eb filloni nj\u00eb projekt?",
      "answer": "Ne ofrojm\u00eb sh\u00ebrbim n\u00eb t\u00eb nj\u00ebjt\u00ebn dit\u00eb p\u00ebr riparime emergjente. P\u00ebr instalime dhe projekte m\u00eb t\u00eb m\u00ebdha, zakonisht mund t\u00eb caktojm\u00eb brenda pak dit\u00ebsh. Telefononi 044 239 757 p\u00ebr t\u00eb kontrolluar disponueshm\u00ebrin\u00eb aktuale."
    }
  ]
}